qai/chat/__init__.py
qai/chat/aws/__init__.py
qai/chat/chat.py
qai/chat/config.py
qai/chat/db/__init__.py
qai/chat/db/chroma/chroma.py
qai/chat/db/chroma/chroma_loader.py
qai/chat/db/retriever.py
qai/chat/db/retriever_factory.py
qai/chat/facts/__init__.py
qai/chat/layers/__init__.py
qai/chat/layers/chatbot.py
qai/chat/layers/fact_table/__init__.py
qai/chat/layers/fact_table/fact.py
qai/chat/layers/fact_table/factory.py
qai/chat/layers/fact_table/table.py
qai/chat/layers/factory.py
qai/chat/layers/layer.py
qai/chat/layers/llm/__init__.py
qai/chat/layers/llm/assistant/assistant_tools.py
qai/chat/layers/llm/chatbot.py
qai/chat/layers/llm/factory.py
qai/chat/layers/query.py
qai/chat/models.py
qai/chat/prompt/__init__.py
qai/chat/prompt/config.py
qai/chat/prompt/prompt_maker.py
qai/chat/prompts.py
qai_chat-0.6.0.dist-info/METADATA
qai_chat-0.6.0.dist-info/WHEEL
qai_chat-0.6.0.dist-info/entry_points.txt
qai_chat-0.6.0.dist-info/RECORD
