Metadata-Version: 2.1
Name: qai-chat
Version: 0.6.0
Summary: 
Author: parnell
Author-email: 152523161+leeparnell@users.noreply.github.com
Requires-Python: >=3.11,<3.12
Classifier: Programming Language :: Python :: 3
Classifier: Programming Language :: Python :: 3.11
Requires-Dist: flask (>=3.0.3,<4.0.0)
Requires-Dist: llama-index (>=0.10.30,<0.11.0)
Requires-Dist: llama-index-llms-openai (>=0.1.16,<0.2.0)
Requires-Dist: llama-index-vector-stores-chroma (>=0.1.6,<0.2.0)
Requires-Dist: openai (>=1.23.2,<2.0.0)
Requires-Dist: pi-conf (>=0.8.5,<0.9.0)
Requires-Dist: pi-log (>=0.5.8.1,<0.6.0.0)
Requires-Dist: python-dotenv (>=1.0.1,<2.0.0)
Requires-Dist: qai-ai (>=0.6.0,<0.7.0)
Requires-Dist: qai-core (>=0.6.0,<0.7.0)
Requires-Dist: torch (==2.3.0+cpu) ; sys_platform == "linux"
Requires-Dist: torch (==2.3.0+cpu) ; sys_platform == "win32"
Requires-Dist: torch (>=2.3.0,<3.0.0) ; sys_platform == "darwin"
Requires-Dist: torch (>=2.3.0,<3.0.0) ; sys_platform == "darwin" and platform_machine == "arm64"
